mm_ptx/__init__.py
mm_ptx/include.py
mm_ptx/include/ptx_inject.h
mm_ptx/include/stack_ptx.h
mm_ptx/include/boost/LICENSE_1_0.txt
mm_ptx/include/boost/preprocessor.hpp
mm_ptx/include/boost/preprocessor/arithmetic.hpp
mm_ptx/include/boost/preprocessor/array.hpp
mm_ptx/include/boost/preprocessor/assert_msg.hpp
mm_ptx/include/boost/preprocessor/cat.hpp
mm_ptx/include/boost/preprocessor/comma.hpp
mm_ptx/include/boost/preprocessor/comma_if.hpp
mm_ptx/include/boost/preprocessor/comparison.hpp
mm_ptx/include/boost/preprocessor/control.hpp
mm_ptx/include/boost/preprocessor/debug.hpp
mm_ptx/include/boost/preprocessor/dec.hpp
mm_ptx/include/boost/preprocessor/empty.hpp
mm_ptx/include/boost/preprocessor/enum.hpp
mm_ptx/include/boost/preprocessor/enum_params.hpp
mm_ptx/include/boost/preprocessor/enum_params_with_a_default.hpp
mm_ptx/include/boost/preprocessor/enum_params_with_defaults.hpp
mm_ptx/include/boost/preprocessor/enum_shifted.hpp
mm_ptx/include/boost/preprocessor/enum_shifted_params.hpp
mm_ptx/include/boost/preprocessor/expand.hpp
mm_ptx/include/boost/preprocessor/expr_if.hpp
mm_ptx/include/boost/preprocessor/facilities.hpp
mm_ptx/include/boost/preprocessor/for.hpp
mm_ptx/include/boost/preprocessor/identity.hpp
mm_ptx/include/boost/preprocessor/if.hpp
mm_ptx/include/boost/preprocessor/inc.hpp
mm_ptx/include/boost/preprocessor/iterate.hpp
mm_ptx/include/boost/preprocessor/iteration.hpp
mm_ptx/include/boost/preprocessor/library.hpp
mm_ptx/include/boost/preprocessor/limits.hpp
mm_ptx/include/boost/preprocessor/list.hpp
mm_ptx/include/boost/preprocessor/logical.hpp
mm_ptx/include/boost/preprocessor/max.hpp
mm_ptx/include/boost/preprocessor/min.hpp
mm_ptx/include/boost/preprocessor/punctuation.hpp
mm_ptx/include/boost/preprocessor/repeat.hpp
mm_ptx/include/boost/preprocessor/repeat_2nd.hpp
mm_ptx/include/boost/preprocessor/repeat_3rd.hpp
mm_ptx/include/boost/preprocessor/repeat_from_to.hpp
mm_ptx-1.0.1.dist-info/METADATA
mm_ptx-1.0.1.dist-info/WHEEL
mm_ptx-1.0.1.dist-info/RECORD
mm_ptx-1.0.1.dist-info/licenses/LICENSE
